live_translation/__init__.py
live_translation/_audio/__init__.py
live_translation/_audio/_codec.py
live_translation/_audio/_processor.py
live_translation/_audio/_vad.py
live_translation/_transcription/__init__.py
live_translation/_transcription/_transcriber.py
live_translation/_translation/__init__.py
live_translation/_translation/_translator.py
live_translation/client/__init__.py
live_translation/client/_args.py
live_translation/client/cli.py
live_translation/client/client.py
live_translation/client/config.py
live_translation/server/__init__.py
live_translation/server/_args.py
live_translation/server/_logger.py
live_translation/server/_pipeline.py
live_translation/server/_ws.py
live_translation/server/cli.py
live_translation/server/config.py
live_translation/server/server.py
live_translation/tools/demo.py
live_translation-0.9.0.dist-info/licenses/LICENSE
live_translation-0.9.0.dist-info/METADATA
live_translation-0.9.0.dist-info/WHEEL
live_translation-0.9.0.dist-info/entry_points.txt
live_translation-0.9.0.dist-info/top_level.txt
live_translation-0.9.0.dist-info/RECORD
