Metadata-Version: 2.4
Name: live-translation
Version: 0.9.0
Summary: A real-time translation tool using Whisper & Opus-MT
Author-email: Abdullah Hendy <abdullah.a.hendy@gmail.com>
License-Expression: MIT
Project-URL: Homepage, https://github.com/AbdullahHendy/live-translation
Project-URL: Repository, https://github.com/AbdullahHendy/live-translation
Keywords: translation,transcription,speech-to-text,real-time translation,whisper,marianMT,Opus-MT,live transcription
Classifier: Development Status :: 4 - Beta
Classifier: Intended Audience :: Developers
Classifier: Intended Audience :: Education
Classifier: Intended Audience :: Science/Research
Classifier: Natural Language :: English
Classifier: Topic :: Multimedia :: Sound/Audio :: Analysis
Classifier: Topic :: Scientific/Engineering :: Artificial Intelligence
Classifier: Topic :: Software Development :: Libraries
Classifier: Topic :: Utilities
Classifier: Environment :: Console
Classifier: Programming Language :: Python :: 3
Classifier: Programming Language :: Python :: 3.11
Classifier: Programming Language :: Python :: 3.12
Classifier: Programming Language :: Python :: 3.13
Requires-Python: >=3.11
License-File: LICENSE
Requires-Dist: torch==2.8.0
Requires-Dist: torchaudio==2.8.0
Requires-Dist: transformers==4.55.0
Requires-Dist: numpy==2.2.3
Requires-Dist: pyaudio==0.2.14
Requires-Dist: websockets==15.0.1
Requires-Dist: huggingface_hub==0.34.4
Requires-Dist: sacremoses==0.1.1
Requires-Dist: faster-whisper==1.2.0
Requires-Dist: sentencepiece==0.2.1
Requires-Dist: opuslib==3.0.1
Provides-Extra: dev
Requires-Dist: psutil==7.0.0; extra == "dev"
Requires-Dist: ruff==0.12.8; extra == "dev"
Requires-Dist: pytest==8.4.1; extra == "dev"
Requires-Dist: coverage==7.10.3; extra == "dev"
Requires-Dist: pytest-asyncio==1.1.0; extra == "dev"
Requires-Dist: soundfile==0.13.1; extra == "dev"
Requires-Dist: build==1.3.0; extra == "dev"
Requires-Dist: twine==6.1.0; extra == "dev"
Provides-Extra: examples
Requires-Dist: opencv-python==4.12.0.88; extra == "examples"
Requires-Dist: pillow==11.3.0; extra == "examples"
Dynamic: license-file
